marshmallow_numerical/__init__.py
marshmallow_numerical/dataframe.py
marshmallow_numerical-0.0.2.dist-info/LICENSE
marshmallow_numerical-0.0.2.dist-info/METADATA
marshmallow_numerical-0.0.2.dist-info/WHEEL
marshmallow_numerical-0.0.2.dist-info/top_level.txt
marshmallow_numerical-0.0.2.dist-info/RECORD
